{
  "endpointId": "light-living",
  "manufacturerName": "IRISOHYAMA",
  "friendlyName": "電気",
  "description": "リビングの電気です",
  "displayCategories": ["LIGHT"],
  "cookie": {},
  "capabilities":
    [
      {
        "type": "AlexaInterface",
        "interface": "Alexa",
        "version": "3"
      },
      {
        "interface": "Alexa.PowerController",
        "version": "3",
        "type": "AlexaInterface",
        "properties": {
          "supported": [{
            "name": "powerState"
          }],
          "retrievable": true
        }
      }
    ]
}